langbot/__init__.py
langbot/__main__.py
langbot/libs/coze_server_api/__init__.py
langbot/libs/coze_server_api/client.py
langbot/libs/dify_service_api/__init__.py
langbot/libs/dify_service_api/v1/__init__.py
langbot/libs/dify_service_api/v1/client.py
langbot/libs/dify_service_api/v1/client_test.py
langbot/libs/dify_service_api/v1/errors.py
langbot/libs/dingtalk_api/EchoHandler.py
langbot/libs/dingtalk_api/__init__.py
langbot/libs/dingtalk_api/api.py
langbot/libs/dingtalk_api/dingtalkevent.py
langbot/libs/official_account_api/__init__.py
langbot/libs/official_account_api/api.py
langbot/libs/official_account_api/oaevent.py
langbot/libs/qq_official_api/__init__.py
langbot/libs/qq_official_api/api.py
langbot/libs/qq_official_api/qqofficialevent.py
langbot/libs/slack_api/__init__.py
langbot/libs/slack_api/api.py
langbot/libs/slack_api/slackevent.py
langbot/libs/wechatpad_api/__init__.py
langbot/libs/wechatpad_api/client.py
langbot/libs/wechatpad_api/api/__init__.py
langbot/libs/wechatpad_api/api/chatroom.py
langbot/libs/wechatpad_api/api/downloadpai.py
langbot/libs/wechatpad_api/api/friend.py
langbot/libs/wechatpad_api/api/login.py
langbot/libs/wechatpad_api/api/message.py
langbot/libs/wechatpad_api/api/user.py
langbot/libs/wechatpad_api/util/__init__.py
langbot/libs/wechatpad_api/util/http_util.py
langbot/libs/wechatpad_api/util/terminal_printer.py
langbot/libs/wecom_ai_bot_api/WXBizMsgCrypt3.py
langbot/libs/wecom_ai_bot_api/api.py
langbot/libs/wecom_ai_bot_api/ierror.py
langbot/libs/wecom_ai_bot_api/wecombotevent.py
langbot/libs/wecom_api/WXBizMsgCrypt3.py
langbot/libs/wecom_api/__init__.py
langbot/libs/wecom_api/api.py
langbot/libs/wecom_api/ierror.py
langbot/libs/wecom_api/wecomevent.py
langbot/libs/wecom_customer_service_api/__init__.py
langbot/libs/wecom_customer_service_api/api.py
langbot/libs/wecom_customer_service_api/wecomcsevent.py
langbot/pkg/__init__.py
langbot/pkg/api/__init__.py
langbot/pkg/api/http/__init__.py
langbot/pkg/api/http/controller/__init__.py
langbot-4.8.2.dist-info/licenses/LICENSE
langbot-4.8.2.dist-info/METADATA
langbot-4.8.2.dist-info/WHEEL
langbot-4.8.2.dist-info/entry_points.txt
langbot-4.8.2.dist-info/top_level.txt
langbot-4.8.2.dist-info/RECORD
