Metadata-Version: 2.4
Name: langbot
Version: 4.8.2
Summary: Production-grade platform for building agentic IM bots
Project-URL: Homepage, https://langbot.app
Project-URL: Documentation, https://docs.langbot.app
Project-URL: Repository, https://github.com/langbot-app/LangBot
Keywords: bot,agent,telegram,plugins,openai,instant-messaging,wechat,qq,dify,llm,chatgpt,deepseek,onebot
Classifier: Development Status :: 5 - Production/Stable
Classifier: Framework :: AsyncIO
Classifier: Framework :: Robot Framework
Classifier: Framework :: Robot Framework :: Library
Classifier: Operating System :: OS Independent
Classifier: Programming Language :: Python :: 3
Classifier: Topic :: Communications :: Chat
Requires-Python: <4.0,>=3.11
License-File: LICENSE
Requires-Dist: aiocqhttp>=1.4.4
Requires-Dist: aiofiles>=24.1.0
Requires-Dist: aiohttp>=3.11.18
Requires-Dist: aioshutil>=1.5
Requires-Dist: aiosqlite>=0.21.0
Requires-Dist: anthropic>=0.51.0
Requires-Dist: argon2-cffi>=23.1.0
Requires-Dist: async-lru>=2.0.5
Requires-Dist: certifi>=2025.4.26
Requires-Dist: colorlog~=6.6.0
Requires-Dist: cryptography>=44.0.3
Requires-Dist: dashscope>=1.23.2
Requires-Dist: dingtalk-stream>=0.24.0
Requires-Dist: discord-py>=2.5.2
Requires-Dist: pynacl>=1.5.0
Requires-Dist: gewechat-client>=0.1.5
Requires-Dist: lark-oapi>=1.4.15
Requires-Dist: mcp>=1.25.0
Requires-Dist: nakuru-project-idk>=0.0.2.1
Requires-Dist: ollama>=0.4.8
Requires-Dist: openai>1.0.0
Requires-Dist: pillow>=11.2.1
Requires-Dist: psutil>=7.0.0
Requires-Dist: pycryptodome>=3.22.0
Requires-Dist: pydantic>2.0
Requires-Dist: pyjwt>=2.10.1
Requires-Dist: python-telegram-bot>=22.0
Requires-Dist: pyyaml>=6.0.2
Requires-Dist: qq-botpy-rc>=1.2.1.6
Requires-Dist: quart>=0.20.0
Requires-Dist: quart-cors>=0.8.0
Requires-Dist: requests>=2.32.3
Requires-Dist: slack-sdk>=3.35.0
Requires-Dist: sqlalchemy[asyncio]>=2.0.40
Requires-Dist: sqlmodel>=0.0.24
Requires-Dist: telegramify-markdown>=0.5.1
Requires-Dist: tiktoken>=0.9.0
Requires-Dist: urllib3>=2.4.0
Requires-Dist: websockets>=15.0.1
Requires-Dist: python-socks>=2.7.1
Requires-Dist: pip>=25.1.1
Requires-Dist: ruff>=0.11.9
Requires-Dist: pre-commit>=4.2.0
Requires-Dist: uv>=0.7.11
Requires-Dist: mypy>=1.16.0
Requires-Dist: PyPDF2>=3.0.1
Requires-Dist: python-docx>=1.1.0
Requires-Dist: pandas>=2.2.2
Requires-Dist: chardet>=5.2.0
Requires-Dist: markdown>=3.6
Requires-Dist: beautifulsoup4>=4.12.3
Requires-Dist: ebooklib>=0.18
Requires-Dist: html2text>=2024.2.26
Requires-Dist: langchain>=0.2.0
Requires-Dist: langchain-text-splitters>=0.0.1
Requires-Dist: chromadb>=0.4.24
Requires-Dist: qdrant-client<2.0.0,>=1.15.1
Requires-Dist: pyseekdb==1.0.0b7
Requires-Dist: langbot-plugin==0.2.5
Requires-Dist: asyncpg>=0.30.0
Requires-Dist: line-bot-sdk>=3.19.0
Requires-Dist: tboxsdk>=0.0.10
Requires-Dist: boto3>=1.35.0
Requires-Dist: pymilvus>=2.6.4
Requires-Dist: pgvector>=0.4.1
Dynamic: license-file
